LICENSE
README.md
setup.py
wiserl/__init__.py
wiserl.egg-info/PKG-INFO
wiserl.egg-info/SOURCES.txt
wiserl.egg-info/dependency_links.txt
wiserl.egg-info/requires.txt
wiserl.egg-info/top_level.txt
wiserl/algorithm/__init__.py
wiserl/algorithm/base.py
wiserl/algorithm/bt_awac.py
wiserl/algorithm/bt_iql.py
wiserl/algorithm/cpl.py
wiserl/algorithm/cpl_kl.py
wiserl/algorithm/ipl_awac.py
wiserl/algorithm/ipl_iql.py
wiserl/algorithm/oracle_awac.py
wiserl/algorithm/oracle_iql.py
wiserl/algorithm/rpl_iql.py
wiserl/algorithm/sft.py
wiserl/dataset/__init__.py
wiserl/dataset/d4rl_dataset.py
wiserl/dataset/ipl_dataset.py
wiserl/dataset/metaworld_dataset.py
wiserl/dataset/replay_buffer.py
wiserl/dataset/robomimic_dataset.py
wiserl/env/__init__.py
wiserl/env/base.py
wiserl/env/metaworld.py
wiserl/eval/__init__.py
wiserl/eval/offline.py
wiserl/module/__init__.py
wiserl/module/actor.py
wiserl/module/critic.py
wiserl/module/net/__init__.py
wiserl/module/net/basic.py
wiserl/module/net/mlp.py
wiserl/processor/__init__.py
wiserl/processor/base.py
wiserl/processor/image_augmentation.py
wiserl/utils/__init__.py
wiserl/utils/distributions.py
wiserl/utils/functional.py
wiserl/utils/misc.py
wiserl/utils/utils.py