Metadata-Version: 2.1
Name: wiserl
Version: 0.0.2
Summary: A library desgined for Offline Preference-Based RL algorithms. 
Home-page: https://github.com/typoverflow/WiseRL
Author: typoverflow
Author-email: typoverflow@outlook.com
License: MIT
Requires-Python: >=3.7
License-File: LICENSE
Requires-Dist: gym<=0.24.1,>=0.23.1
Requires-Dist: tqdm
Requires-Dist: numpy
Requires-Dist: torch
Requires-Dist: torchvisionpandas
Requires-Dist: UtilsRL
